html_text_color/__init__.py
html_text_color/create_colored.py
html_text_color/test.py
html_text_color/util.py
html_text_color-0.0.10.dist-info/METADATA
html_text_color-0.0.10.dist-info/WHEEL
html_text_color-0.0.10.dist-info/licenses/LICENSE
html_text_color-0.0.10.dist-info/RECORD
