Metadata-Version: 2.3
Name: html_text_color
Version: 0.0.10
Summary: Visualize number vector on text using colored html
Author-email: Yannik Keller <yannik@kelnet.de>
License: MIT License
License-File: LICENSE
Keywords: HTML,Language Model,color,text,visualization
Requires-Python: >=3.6
Requires-Dist: matplotlib
Requires-Dist: numpy
